<Response xmlns:xsi="http://www.w3.org/2001/XMLSchema-instance" xmlns:xsd="http://www.w3.org/2001/XMLSchema"><Count>56</Count><Message>Response returned successfully</Message><SearchCriteria>Make:ferrari</SearchCriteria><Results><ModelsForMake><Make_ID>603</Make_ID><Make_Name>Ferrari</Make_Name><Model_ID>3601</Model_ID><Model_Name>612 Scaglietti</Model_Name></ModelsForMake><ModelsForMake><Make_ID>603</Make_ID><Make_Name>Ferrari</Make_Name><Model_ID>3602</Model_ID><Model_Name>F430 Coupe</Model_Name></ModelsForMake><ModelsForMake><Make_ID>603</Make_ID><Make_Name>Ferrari</Make_Name><Model_ID>3603</Model_ID><Model_Name>599 GTB</Model_Name></ModelsForMake><ModelsForMake><Make_ID>603</Make_ID><Make_Name>Ferrari</Make_Name><Model_ID>3604</Model_ID><Model_Name>F430 Spider</Model_Name></ModelsForMake><ModelsForMake><Make_ID>603</Make_ID><Make_Name>Ferrari</Make_Name><Model_ID>3605</Model_ID><Model_Name>599 GTB Fiorano</Model_Name></ModelsForMake><ModelsForMake><Make_ID>603</Make_ID><Make_Name>Ferrari</Make_Name><Model_ID>3606</Model_ID><Model_Name>430 Scuderia</Model_Name></ModelsForMake><ModelsForMake><Make_ID>603</Make_ID><Make_Name>Ferrari</Make_Name><Model_ID>3607</Model_ID><Model_Name>F430</Model_Name></ModelsForMake><ModelsForMake><Make_ID>603</Make_ID><Make_Name>Ferrari</Make_Name><Model_ID>3635</Model_ID><Model_Name>430 Scuderia Spider</Model_Name></ModelsForMake><ModelsForMake><Make_ID>603</Make_ID><Make_Name>Ferrari</Make_Name><Model_ID>9939</Model_ID><Model_Name>360 Modena/360 Modena F1</Model_Name></ModelsForMake><ModelsForMake><Make_ID>603</Make_ID><Make_Name>Ferrari</Make_Name><Model_ID>9940</Model_ID><Model_Name>360 Spider/360 Spider F1</Model_Name></ModelsForMake><ModelsForMake><Make_ID>603</Make_ID><Make_Name>Ferrari</Make_Name><Model_ID>9941</Model_ID><Model_Name>575 M Maranello/575 M Maranello F1</Model_Name></ModelsForMake><ModelsForMake><Make_ID>603</Make_ID><Make_Name>Ferrari</Make_Name><Model_ID>9942</Model_ID><Model_Name>456 MGT</Model_Name></ModelsForMake><ModelsForMake><Make_ID>603</Make_ID><Make_Name>Ferrari</Make_Name><Model_ID>9943</Model_ID><Model_Name>456 MGTA</Model_Name></ModelsForMake><ModelsForMake><Make_ID>603</Make_ID><Make_Name>Ferrari</Make_Name><Model_ID>9944</Model_ID><Model_Name>Enzo</Model_Name></ModelsForMake><ModelsForMake><Make_ID>603</Make_ID><Make_Name>Ferrari</Make_Name><Model_ID>9954</Model_ID><Model_Name>F355</Model_Name></ModelsForMake><ModelsForMake><Make_ID>603</Make_ID><Make_Name>Ferrari</Make_Name><Model_ID>9957</Model_ID><Model_Name>550 Maranello</Model_Name></ModelsForMake><ModelsForMake><Make_ID>603</Make_ID><Make_Name>Ferrari</Make_Name><Model_ID>13843</Model_ID><Model_Name>F12 Berlinetta</Model_Name></ModelsForMake><ModelsForMake><Make_ID>603</Make_ID><Make_Name>Ferrari</Make_Name><Model_ID>13849</Model_ID><Model_Name>California T</Model_Name></ModelsForMake><ModelsForMake><Make_ID>603</Make_ID><Make_Name>Ferrari</Make_Name><Model_ID>13850</Model_ID><Model_Name>FF</Model_Name></ModelsForMake><ModelsForMake><Make_ID>603</Make_ID><Make_Name>Ferrari</Make_Name><Model_ID>13851</Model_ID><Model_Name>La Ferrari</Model_Name></ModelsForMake><ModelsForMake><Make_ID>603</Make_ID><Make_Name>Ferrari</Make_Name><Model_ID>13852</Model_ID><Model_Name>458 Italia</Model_Name></ModelsForMake><ModelsForMake><Make_ID>603</Make_ID><Make_Name>Ferrari</Make_Name><Model_ID>13853</Model_ID><Model_Name>458 Speciale</Model_Name></ModelsForMake><ModelsForMake><Make_ID>603</Make_ID><Make_Name>Ferrari</Make_Name><Model_ID>13854</Model_ID><Model_Name>458 Speciale Spider</Model_Name></ModelsForMake><ModelsForMake><Make_ID>603</Make_ID><Make_Name>Ferrari</Make_Name><Model_ID>13855</Model_ID><Model_Name>458 Spider</Model_Name></ModelsForMake><ModelsForMake><Make_ID>603</Make_ID><Make_Name>Ferrari</Make_Name><Model_ID>13856</Model_ID><Model_Name>California</Model_Name></ModelsForMake><ModelsForMake><Make_ID>603</Make_ID><Make_Name>Ferrari</Make_Name><Model_ID>13872</Model_ID><Model_Name>599 GTO</Model_Name></ModelsForMake><ModelsForMake><Make_ID>603</Make_ID><Make_Name>Ferrari</Make_Name><Model_ID>14016</Model_ID><Model_Name>348 tb</Model_Name></ModelsForMake><ModelsForMake><Make_ID>603</Make_ID><Make_Name>Ferrari</Make_Name><Model_ID>14017</Model_ID><Model_Name>348 ts</Model_Name></ModelsForMake><ModelsForMake><Make_ID>603</Make_ID><Make_Name>Ferrari</Make_Name><Model_ID>14020</Model_ID><Model_Name>512 TR</Model_Name></ModelsForMake><ModelsForMake><Make_ID>603</Make_ID><Make_Name>Ferrari</Make_Name><Model_ID>14024</Model_ID><Model_Name>355 Berlinetta</Model_Name></ModelsForMake><ModelsForMake><Make_ID>603</Make_ID><Make_Name>Ferrari</Make_Name><Model_ID>14025</Model_ID><Model_Name>355 GTS</Model_Name></ModelsForMake><ModelsForMake><Make_ID>603</Make_ID><Make_Name>Ferrari</Make_Name><Model_ID>14026</Model_ID><Model_Name>348 Spider</Model_Name></ModelsForMake><ModelsForMake><Make_ID>603</Make_ID><Make_Name>Ferrari</Make_Name><Model_ID>14027</Model_ID><Model_Name>456 GT</Model_Name></ModelsForMake><ModelsForMake><Make_ID>603</Make_ID><Make_Name>Ferrari</Make_Name><Model_ID>14028</Model_ID><Model_Name>355 Spider</Model_Name></ModelsForMake><ModelsForMake><Make_ID>603</Make_ID><Make_Name>Ferrari</Make_Name><Model_ID>14031</Model_ID><Model_Name>Mondial T</Model_Name></ModelsForMake><ModelsForMake><Make_ID>603</Make_ID><Make_Name>Ferrari</Make_Name><Model_ID>14038</Model_ID><Model_Name>Testarossa</Model_Name></ModelsForMake><ModelsForMake><Make_ID>603</Make_ID><Make_Name>Ferrari</Make_Name><Model_ID>14039</Model_ID><Model_Name>F40</Model_Name></ModelsForMake><ModelsForMake><Make_ID>603</Make_ID><Make_Name>Ferrari</Make_Name><Model_ID>14047</Model_ID><Model_Name>328 GTB</Model_Name></ModelsForMake><ModelsForMake><Make_ID>603</Make_ID><Make_Name>Ferrari</Make_Name><Model_ID>14048</Model_ID><Model_Name>328 GTS</Model_Name></ModelsForMake><ModelsForMake><Make_ID>603</Make_ID><Make_Name>Ferrari</Make_Name><Model_ID>14049</Model_ID><Model_Name>3.2 Mondial</Model_Name></ModelsForMake><ModelsForMake><Make_ID>603</Make_ID><Make_Name>Ferrari</Make_Name><Model_ID>14050</Model_ID><Model_Name>328</Model_Name></ModelsForMake><ModelsForMake><Make_ID>603</Make_ID><Make_Name>Ferrari</Make_Name><Model_ID>14052</Model_ID><Model_Name>308GTB Quattrovalvole</Model_Name></ModelsForMake><ModelsForMake><Make_ID>603</Make_ID><Make_Name>Ferrari</Make_Name><Model_ID>14053</Model_ID><Model_Name>308GTS Quattrovalvole</Model_Name></ModelsForMake><ModelsForMake><Make_ID>603</Make_ID><Make_Name>Ferrari</Make_Name><Model_ID>14054</Model_ID><Model_Name>Mondial Quattrovalvole</Model_Name></ModelsForMake><ModelsForMake><Make_ID>603</Make_ID><Make_Name>Ferrari</Make_Name><Model_ID>14055</Model_ID><Model_Name>Mondial 8</Model_Name></ModelsForMake><ModelsForMake><Make_ID>603</Make_ID><Make_Name>Ferrari</Make_Name><Model_ID>14056</Model_ID><Model_Name>308 Convertible</Model_Name></ModelsForMake><ModelsForMake><Make_ID>603</Make_ID><Make_Name>Ferrari</Make_Name><Model_ID>14111</Model_ID><Model_Name>488 GTB</Model_Name></ModelsForMake><ModelsForMake><Make_ID>603</Make_ID><Make_Name>Ferrari</Make_Name><Model_ID>14112</Model_ID><Model_Name>488 GTS</Model_Name></ModelsForMake><ModelsForMake><Make_ID>603</Make_ID><Make_Name>Ferrari</Make_Name><Model_ID>14113</Model_ID><Model_Name>F12 Special Series</Model_Name></ModelsForMake><ModelsForMake><Make_ID>603</Make_ID><Make_Name>Ferrari</Make_Name><Model_ID>14114</Model_ID><Model_Name>F60 America</Model_Name></ModelsForMake><ModelsForMake><Make_ID>603</Make_ID><Make_Name>Ferrari</Make_Name><Model_ID>14598</Model_ID><Model_Name>308GTBi</Model_Name></ModelsForMake><ModelsForMake><Make_ID>603</Make_ID><Make_Name>Ferrari</Make_Name><Model_ID>14599</Model_ID><Model_Name>308GTSi</Model_Name></ModelsForMake><ModelsForMake><Make_ID>603</Make_ID><Make_Name>Ferrari</Make_Name><Model_ID>14600</Model_ID><Model_Name>308GTB</Model_Name></ModelsForMake><ModelsForMake><Make_ID>603</Make_ID><Make_Name>Ferrari</Make_Name><Model_ID>14601</Model_ID><Model_Name>308GTS</Model_Name></ModelsForMake><ModelsForMake><Make_ID>603</Make_ID><Make_Name>Ferrari</Make_Name><Model_ID>25180</Model_ID><Model_Name>F12 tdf (Tour de France)</Model_Name></ModelsForMake><ModelsForMake><Make_ID>603</Make_ID><Make_Name>Ferrari</Make_Name><Model_ID>25181</Model_ID><Model_Name>GTC4Lusso</Model_Name></ModelsForMake></Results></Response>